tinydag/__init__.py
tinydag/dask_example.py
tinydag/exceptions.py
tinydag/graph.py
tinydag/node.py
tinydag/internal/__init__.py
tinydag/internal/node_runner.py
tinydag/internal/node_runner_dict_based_works.py
tinydag/internal/node_runner_queue_based.py
tinydag/internal/rendering.py
tinydag/internal/utils.py
tiny_dag-0.0.18.dist-info/LICENSE
tiny_dag-0.0.18.dist-info/METADATA
tiny_dag-0.0.18.dist-info/WHEEL
tiny_dag-0.0.18.dist-info/top_level.txt
tiny_dag-0.0.18.dist-info/RECORD
