Metadata-Version: 2.1
Name: tiny-dag
Version: 0.0.18
Summary: Minimal DAG implementation with Python
Home-page: https://github.com/omyllymaki/tiny-dag
Author: Ossi Myllymäki
Author-email: omyllymaki@gmail.com
Project-URL: Bug Tracker, https://github.com/omyllymaki/tiny-dag/issues
Classifier: Programming Language :: Python :: 3
Classifier: License :: OSI Approved :: MIT License
Classifier: Operating System :: OS Independent
Requires-Python: >=3.6
License-File: LICENSE
Requires-Dist: graphviz
